README.rst
setup.py
PyV4L2Camera/__init__.py
PyV4L2Camera/camera.c
PyV4L2Camera/controls.c
PyV4L2Camera/exceptions.py
PyV4L2Camera.egg-info/PKG-INFO
PyV4L2Camera.egg-info/SOURCES.txt
PyV4L2Camera.egg-info/dependency_links.txt
PyV4L2Camera.egg-info/requires.txt
PyV4L2Camera.egg-info/top_level.txt