Metadata-Version: 1.0
Name: PyV4L2Camera
Version: 0.1a2
Summary: Simple, libv4l2 based frame grabber
Home-page: https://gitlab.com/radish/PyV4L2Camera
Author: Dominik Pieczyński
Author-email: dominik.pieczynski@gmail.com
License: GNU Lesser General Public License v3 (LGPLv3)
Platform: UNKNOWN
